[
  {
    "id": "46c2fdce-6c99-43d9-b372-4df5bfde4415",
    "email": "keisahb@gmail.com",
    "plan_type": "free"
  },
  {
    "id": "7a14d63b-78f6-4726-bc17-57bad3219905",
    "email": "2205688@students.kcau.ac.ke",
    "plan_type": "free"
  },
  {
    "id": "62fbec9f-abe3-420e-9de0-e22fda95a269",
    "email": "mwitaben23@gmail.com",
    "plan_type": "free"
  },
  {
    "id": "3f348693-f550-432e-bf33-51b95fda25b1",
    "email": "deborahbosire123@gmail.com",
    "plan_type": "free"
  },
  {
    "id": "7f0978e6-c60e-4d46-b772-1b925178c211",
    "email": "kwambokafaith071@gmail.com",
    "plan_type": "free"
  },
  {
    "id": "300a70d8-fc11-40d0-8996-8b6145146ea1",
    "email": "tabbybosire@gmail.com",
    "plan_type": "free"
  },
  {
    "id": "6d3ea391-64d0-42ee-8130-b9679d8a204e",
    "email": "airtel3064@gmail.com",
    "plan_type": "free"
  },
  {
    "id": "b0e584b0-114a-4273-b257-640647026173",
    "email": "kemuma3064@gmail.com",
    "plan_type": "free"
  },
  {
    "id": "f2490192-e51e-434e-a806-6abe3aa44869",
    "email": "velma5637@gmail.com",
    "plan_type": "free"
  },
  {
    "id": "e3d3e6ce-3564-4a49-91ef-ffa36976725f",
    "email": "hakinola20@gmail.com",
    "plan_type": "free"
  },
  {
    "id": "d2185b4e-9453-443c-a572-d39b253f7ee6",
    "email": "stomzyelectronics@gmail.com",
    "plan_type": "free"
  },
  {
    "id": "58476a00-5b23-48ea-b092-856f9e9981d5",
    "email": "deborahbosire01@gmail.com",
    "plan_type": "free"
  },
  {
    "id": "1ee062f8-5f4c-441c-94d8-eb7e0f8028c5",
    "email": "rosesschoolchic@gmail.com",
    "plan_type": "free"
  },
  {
    "id": "d0c952b8-e88d-4f83-b446-949194a12f90",
    "email": "cliffmomanyi32@gmail.com",
    "plan_type": "free"
  },
  {
    "id": "57e3dc63-c54c-4d2d-8711-70eb55195daf",
    "email": "alphadoane@gmail.com",
    "plan_type": "free"
  },
  {
    "id": "c12a1d8d-b380-4e44-b39b-51ad55c71fa1",
    "email": "lame3064@gmail.com",
    "plan_type": "gold"
  },
  {
    "id": "be8555b9-4e9a-400b-b92f-c237da5059a3",
    "email": "lameckonlineshop@gmail.com",
    "plan_type": "free"
  }
]
